fraudlabspro/__init__.py
fraudlabspro/fraudvalidation.py
fraudlabspro/smsverification.py
fraudlabspro_python-3.0.3.dist-info/LICENSE
fraudlabspro_python-3.0.3.dist-info/METADATA
fraudlabspro_python-3.0.3.dist-info/WHEEL
fraudlabspro_python-3.0.3.dist-info/top_level.txt
fraudlabspro_python-3.0.3.dist-info/RECORD
